uiro
