Metadata-Version: 1.1
Name: uiro
Version: 0.2
Summary: le Web framework.
Home-page: https://github.com/hirokiky/uiro/
Author: Hiroki KIYOHARA
Author-email: hirokiky@gmail.com
License: MIT
Keywords: web wsgi
Platform: UNKNOWN
Classifier: Development Status :: 2 - Pre-Alpha
Classifier: Intended Audience :: Developers
Classifier: Programming Language :: Python
Classifier: Programming Language :: Python :: 3
Classifier: Programming Language :: Python :: 3.3
Classifier: Programming Language :: Python :: Implementation :: CPython
Classifier: Topic :: Internet :: WWW/HTTP
Classifier: Topic :: Internet :: WWW/HTTP :: WSGI
Classifier: License :: OSI Approved :: MIT License
